MANIFEST.in
README.txt
setup.cfg
setup.py
docs/HISTORY.txt
horae/__init__.py
horae.timeaware.egg-info/PKG-INFO
horae.timeaware.egg-info/SOURCES.txt
horae.timeaware.egg-info/dependency_links.txt
horae.timeaware.egg-info/entry_points.txt
horae.timeaware.egg-info/namespace_packages.txt
horae.timeaware.egg-info/not-zip-safe
horae.timeaware.egg-info/requires.txt
horae.timeaware.egg-info/top_level.txt
horae/timeaware/__init__.py
horae/timeaware/configure.zcml
horae/timeaware/interfaces.py
horae/timeaware/tests.py
horae/timeaware/timeaware.py
horae/timeaware/timeaware.txt
horae/timeaware/vocabulary.py
horae/timeaware/locales/horae.timeaware.pot
horae/timeaware/locales/de/LC_MESSAGES/horae.timeaware.mo
horae/timeaware/locales/de/LC_MESSAGES/horae.timeaware.po